{ "result": [
  {
    "sum":248,
    "category":"Food",
    "where":"New York",
    "age":"20-30",
    "social":"Student",
    "lives":"Stockholm"
  },
  {
    "sum":280,
    "category":"Housing",
    "where":"Paris",
    "age":"30-40",
    "social":"Working",
    "lives":"Göteborg"
  },
  {
    "sum":288,
    "category":"Nightlife",
    "where":"Madrid",
    "age":"40-50",
    "social":"Working",
    "lives":"Malmö"
  },
  {
    "sum":102,
    "category":"Culture",
    "where":"London",
    "age":"50-60",
    "social":"Working",
    "lives":"Norrland"
  },
  {
    "sum":394,
    "category":"Sports",
    "where":"San Fransisco",
    "age":"60-",
    "social":"Retired",
    "lives":"Norrland"
  },
  {
    "sum":195,
    "category":"Transportation",
    "where":"Hong Kong",
    "age":"20-30",
    "social":"Retired",
    "lives":"Gotland"
  },
  {
    "sum":146,
    "category":"Food",
    "where":"Madrid",
    "age":"20-31",
    "social":"Student",
    "lives":"Stockholm"
  },
  {
    "sum":341,
    "category":"Housing",
    "where":"New York",
    "age":"20-32",
    "social":"Student",
    "lives":"Stockholm"
  },
  {
    "sum":364,
    "category":"Nightlife",
    "where":"New York",
    "age":"20-33",
    "social":"Working",
    "lives":"Göteborg"
  },
  {
    "sum":216,
    "category":"Culture",
    "where":"Paris",
    "age":"20-34",
    "social":"Working",
    "lives":"Göteborg"
  },
  {
    "sum":278,
    "category":"Sports",
    "where":"Paris",
    "age":"30-40",
    "social":"Working",
    "lives":"Stockholm"
  },
  {
    "sum":186,
    "category":"Transportation",
    "where":"New York",
    "age":"30-41",
    "social":"Retired",
    "lives":"Stockholm"
  },
  {
    "sum":255,
    "category":"Food",
    "where":"London",
    "age":"30-42",
    "social":"Retired",
    "lives":"Göteborg"
  },
  {
    "sum":336,
    "category":"Food",
    "where":"New York",
    "age":"30-43",
    "social":"Student",
    "lives":"Malmö"
  },
  {
    "sum":238,
    "category":"Housing",
    "where":"Paris",
    "age":"30-44",
    "social":"Student",
    "lives":"Norrland"
  },
  {
    "sum":311,
    "category":"Nightlife",
    "where":"Madrid",
    "age":"40-50",
    "social":"Working",
    "lives":"Norrland"
  },
  {
    "sum":179,
    "category":"Culture",
    "where":"London",
    "age":"40-51",
    "social":"Working",
    "lives":"Gotland"
  },
  {
    "sum":360,
    "category":"Sports",
    "where":"San Fransisco",
    "age":"40-52",
    "social":"Working",
    "lives":"Stockholm"
  },
  {
    "sum":265,
    "category":"Transportation",
    "where":"Hong Kong",
    "age":"40-53",
    "social":"Retired",
    "lives":"Stockholm"
  },
  {
    "sum":297,
    "category":"Food",
    "where":"Madrid",
    "age":"40-54",
    "social":"Retired",
    "lives":"Göteborg"
  },
  {
    "sum":209,
    "category":"Housing",
    "where":"New York",
    "age":"40-55",
    "social":"Student",
    "lives":"Göteborg"
  },
  {
    "sum":392,
    "category":"Nightlife",
    "where":"New York",
    "age":"50-60",
    "social":"Student",
    "lives":"Stockholm"
  },
  {
    "sum":330,
    "category":"Culture",
    "where":"Paris",
    "age":"60-",
    "social":"Working",
    "lives":"Stockholm"
  },
  {
    "sum":261,
    "category":"Sports",
    "where":"Paris",
    "age":"20-35",
    "social":"Working",
    "lives":"Göteborg"
  },
  {
    "sum":325,
    "category":"Transportation",
    "where":"New York",
    "age":"20-36",
    "social":"Working",
    "lives":"Malmö"
  },
  {
    "sum":38,
    "category":"Food",
    "where":"London",
    "age":"20-37",
    "social":"Retired",
    "lives":"Norrland"
  },
  {
    "sum":105,
    "category":"Food",
    "where":"New York",
    "age":"20-38",
    "social":"Retired",
    "lives":"Norrland"
  },
  {
    "sum":380,
    "category":"Housing",
    "where":"Paris",
    "age":"20-39",
    "social":"Student",
    "lives":"Gotland"
  },
  {
    "sum":121,
    "category":"Nightlife",
    "where":"Madrid",
    "age":"30-45",
    "social":"Student",
    "lives":"Stockholm"
  },
  {
    "sum":220,
    "category":"Culture",
    "where":"London",
    "age":"30-46",
    "social":"Working",
    "lives":"Stockholm"
  },
  {
    "sum":280,
    "category":"Food",
    "where":"New York",
    "age":"30-47",
    "social":"Working",
    "lives":"Göteborg"
  },
  {
    "sum":170,
    "category":"Housing",
    "where":"Paris",
    "age":"30-48",
    "social":"Working",
    "lives":"Göteborg"
  },
  {
    "sum":318,
    "category":"Nightlife",
    "where":"Madrid",
    "age":"30-49",
    "social":"Retired",
    "lives":"Stockholm"
  },
  {
    "sum":102,
    "category":"Culture",
    "where":"London",
    "age":"40-56",
    "social":"Retired",
    "lives":"Stockholm"
  },
  {
    "sum":279,
    "category":"Sports",
    "where":"San Fransisco",
    "age":"40-57",
    "social":"Student",
    "lives":"Göteborg"
  },
  {
    "sum":271,
    "category":"Transportation",
    "where":"Hong Kong",
    "age":"40-58",
    "social":"Student",
    "lives":"Malmö"
  },
  {
    "sum":271,
    "category":"Food",
    "where":"Madrid",
    "age":"40-59",
    "social":"Working",
    "lives":"Norrland"
  },
  {
    "sum":135,
    "category":"Housing",
    "where":"New York",
    "age":"40-60",
    "social":"Working",
    "lives":"Norrland"
  },
  {
    "sum":302,
    "category":"Nightlife",
    "where":"New York",
    "age":"40-61",
    "social":"Working",
    "lives":"Gotland"
  },
  {
    "sum":292,
    "category":"Culture",
    "where":"Paris",
    "age":"50-61",
    "social":"Retired",
    "lives":"Stockholm"
  },
  {
    "sum":180,
    "category":"Sports",
    "where":"Paris",
    "age":"60-",
    "social":"Retired",
    "lives":"Stockholm"
  },
  {
    "sum":185,
    "category":"Transportation",
    "where":"New York",
    "age":"20-40",
    "social":"Student",
    "lives":"Göteborg"
  },
  {
    "sum":178,
    "category":"Food",
    "where":"London",
    "age":"20-41",
    "social":"Student",
    "lives":"Göteborg"
  },
  {
    "sum":35,
    "category":"Food",
    "where":"New York",
    "age":"20-42",
    "social":"Working",
    "lives":"Stockholm"
  },
  {
    "sum":386,
    "category":"Housing",
    "where":"Paris",
    "age":"20-43",
    "social":"Working",
    "lives":"Stockholm"
  },
  {
    "sum":118,
    "category":"Nightlife",
    "where":"Madrid",
    "age":"20-44",
    "social":"Working",
    "lives":"Göteborg"
  },
  {
    "sum":139,
    "category":"Culture",
    "where":"London",
    "age":"30-50",
    "social":"Retired",
    "lives":"Malmö"
  },
  {
    "sum":130,
    "category":"Sports",
    "where":"San Fransisco",
    "age":"30-51",
    "social":"Retired",
    "lives":"Norrland"
  },
  {
    "sum":82,
    "category":"Transportation",
    "where":"Hong Kong",
    "age":"30-52",
    "social":"Student",
    "lives":"Norrland"
  },
  {
    "sum":257,
    "category":"Food",
    "where":"Madrid",
    "age":"30-53",
    "social":"Student",
    "lives":"Gotland"
  },
  {
    "sum":338,
    "category":"Housing",
    "where":"New York",
    "age":"30-54",
    "social":"Working",
    "lives":"Stockholm"
  },
  {
    "sum":111,
    "category":"Nightlife",
    "where":"New York",
    "age":"40-62",
    "social":"Working",
    "lives":"Stockholm"
  },
  {
    "sum":336,
    "category":"Culture",
    "where":"Paris",
    "age":"40-63",
    "social":"Working",
    "lives":"Göteborg"
  },
  {
    "sum":244,
    "category":"Sports",
    "where":"Paris",
    "age":"40-64",
    "social":"Retired",
    "lives":"Göteborg"
  },
  {
    "sum":58,
    "category":"Transportation",
    "where":"New York",
    "age":"40-65",
    "social":"Retired",
    "lives":"Stockholm"
  },
  {
    "sum":169,
    "category":"Food",
    "where":"London",
    "age":"40-66",
    "social":"Student",
    "lives":"Stockholm"
  },
  {
    "sum":169,
    "category":"Food",
    "where":"New York",
    "age":"40-67",
    "social":"Student",
    "lives":"Göteborg"
  },
  {
    "sum":36,
    "category":"Housing",
    "where":"Paris",
    "age":"50-62",
    "social":"Working",
    "lives":"Malmö"
  },
  {
    "sum":383,
    "category":"Nightlife",
    "where":"Madrid",
    "age":"60-",
    "social":"Working",
    "lives":"Norrland"
  },
  {
    "sum":224,
    "category":"Culture",
    "where":"London",
    "age":"20-45",
    "social":"Working",
    "lives":"Norrland"
  },
  {
    "sum":239,
    "category":"Food",
    "where":"New York",
    "age":"20-46",
    "social":"Retired",
    "lives":"Gotland"
  },
  {
    "sum":35,
    "category":"Housing",
    "where":"Paris",
    "age":"20-47",
    "social":"Retired",
    "lives":"Stockholm"
  },
  {
    "sum":328,
    "category":"Nightlife",
    "where":"Madrid",
    "age":"20-48",
    "social":"Student",
    "lives":"Stockholm"
  },
  {
    "sum":91,
    "category":"Culture",
    "where":"London",
    "age":"20-49",
    "social":"Student",
    "lives":"Göteborg"
  },
  {
    "sum":90,
    "category":"Sports",
    "where":"San Fransisco",
    "age":"30-55",
    "social":"Working",
    "lives":"Göteborg"
  },
  {
    "sum":83,
    "category":"Transportation",
    "where":"Hong Kong",
    "age":"30-56",
    "social":"Working",
    "lives":"Stockholm"
  },
  {
    "sum":108,
    "category":"Food",
    "where":"Madrid",
    "age":"30-57",
    "social":"Working",
    "lives":"Stockholm"
  },
  {
    "sum":48,
    "category":"Housing",
    "where":"New York",
    "age":"30-58",
    "social":"Retired",
    "lives":"Göteborg"
  },
  {
    "sum":101,
    "category":"Nightlife",
    "where":"New York",
    "age":"30-59",
    "social":"Retired",
    "lives":"Malmö"
  },
  {
    "sum":43,
    "category":"Culture",
    "where":"Paris",
    "age":"40-68",
    "social":"Student",
    "lives":"Norrland"
  },
  {
    "sum":237,
    "category":"Sports",
    "where":"Paris",
    "age":"40-69",
    "social":"Student",
    "lives":"Norrland"
  },
  {
    "sum":206,
    "category":"Transportation",
    "where":"New York",
    "age":"40-70",
    "social":"Working",
    "lives":"Gotland"
  },
  {
    "sum":185,
    "category":"Food",
    "where":"London",
    "age":"40-71",
    "social":"Working",
    "lives":"Stockholm"
  },
  {
    "sum":322,
    "category":"Food",
    "where":"New York",
    "age":"40-72",
    "social":"Working",
    "lives":"Stockholm"
  },
  {
    "sum":334,
    "category":"Housing",
    "where":"Paris",
    "age":"40-73",
    "social":"Retired",
    "lives":"Göteborg"
  },
  {
    "sum":389,
    "category":"Nightlife",
    "where":"Madrid",
    "age":"50-63",
    "social":"Retired",
    "lives":"Göteborg"
  },
  {
    "sum":42,
    "category":"Culture",
    "where":"London",
    "age":"60-",
    "social":"Student",
    "lives":"Stockholm"
  },
  {
    "sum":59,
    "category":"Sports",
    "where":"San Fransisco",
    "age":"20-50",
    "social":"Student",
    "lives":"Stockholm"
  },
  {
    "sum":146,
    "category":"Transportation",
    "where":"Hong Kong",
    "age":"20-51",
    "social":"Working",
    "lives":"Göteborg"
  },
  {
    "sum":53,
    "category":"Food",
    "where":"Madrid",
    "age":"20-52",
    "social":"Working",
    "lives":"Malmö"
  },
  {
    "sum":151,
    "category":"Housing",
    "where":"New York",
    "age":"20-53",
    "social":"Working",
    "lives":"Norrland"
  },
  {
    "sum":375,
    "category":"Nightlife",
    "where":"New York",
    "age":"20-54",
    "social":"Retired",
    "lives":"Norrland"
  },
  {
    "sum":224,
    "category":"Culture",
    "where":"Paris",
    "age":"30-60",
    "social":"Retired",
    "lives":"Gotland"
  },
  {
    "sum":248,
    "category":"Sports",
    "where":"Paris",
    "age":"30-61",
    "social":"Student",
    "lives":"Stockholm"
  },
  {
    "sum":275,
    "category":"Transportation",
    "where":"New York",
    "age":"30-62",
    "social":"Student",
    "lives":"Stockholm"
  },
  {
    "sum":173,
    "category":"Food",
    "where":"London",
    "age":"30-63",
    "social":"Working",
    "lives":"Göteborg"
  },
  {
    "sum":29,
    "category":"Food",
    "where":"New York",
    "age":"30-64",
    "social":"Working",
    "lives":"Göteborg"
  },
  {
    "sum":312,
    "category":"Housing",
    "where":"Paris",
    "age":"40-74",
    "social":"Working",
    "lives":"Stockholm"
  },
  {
    "sum":61,
    "category":"Nightlife",
    "where":"Madrid",
    "age":"40-75",
    "social":"Retired",
    "lives":"Stockholm"
  },
  {
    "sum":389,
    "category":"Culture",
    "where":"London",
    "age":"40-76",
    "social":"Retired",
    "lives":"Göteborg"
  },
  {
    "sum":399,
    "category":"Food",
    "where":"New York",
    "age":"40-77",
    "social":"Student",
    "lives":"Malmö"
  },
  {
    "sum":59,
    "category":"Housing",
    "where":"Paris",
    "age":"40-78",
    "social":"Student",
    "lives":"Norrland"
  },
  {
    "sum":122,
    "category":"Nightlife",
    "where":"Madrid",
    "age":"40-79",
    "social":"Working",
    "lives":"Norrland"
  },
  {
    "sum":69,
    "category":"Culture",
    "where":"London",
    "age":"50-64",
    "social":"Working",
    "lives":"Gotland"
  },
  {
    "sum":123,
    "category":"Sports",
    "where":"San Fransisco",
    "age":"60-",
    "social":"Working",
    "lives":"Stockholm"
  },
  {
    "sum":199,
    "category":"Transportation",
    "where":"Hong Kong",
    "age":"20-55",
    "social":"Retired",
    "lives":"Stockholm"
  },
  {
    "sum":143,
    "category":"Food",
    "where":"Madrid",
    "age":"20-56",
    "social":"Retired",
    "lives":"Göteborg"
  },
  {
    "sum":302,
    "category":"Housing",
    "where":"New York",
    "age":"20-57",
    "social":"Student",
    "lives":"Göteborg"
  },
  {
    "sum":139,
    "category":"Nightlife",
    "where":"New York",
    "age":"20-58",
    "social":"Student",
    "lives":"Stockholm"
  }
]}